ioknife/__init__.py
ioknife/__main__.py
ioknife/_contextlib_py36.py
ioknife/aioutils.py
ioknife/cli.py
ioknife/too.py
ioknife-0.2.0.dist-info/METADATA
ioknife-0.2.0.dist-info/WHEEL
ioknife-0.2.0.dist-info/entry_points.txt
ioknife-0.2.0.dist-info/top_level.txt
ioknife-0.2.0.dist-info/RECORD
